fogdb/__init__.py
fogdb-0.0.9.dist-info/LICENSE
fogdb-0.0.9.dist-info/WHEEL
fogdb-0.0.9.dist-info/METADATA
fogdb-0.0.9.dist-info/RECORD
