Metadata-Version: 2.1
Name: fogdb
Version: 0.0.9
Summary: Forest Garden Database API
Home-page: https://github.com/tZ3ma/fogdb
License: MIT
Keywords: forest-garden,database,cassandra,api
Author: Mathias Ammon
Author-email: mathias.ammon@tuhh.de
Requires-Python: >=3.8,<4.0
Classifier: License :: OSI Approved :: MIT License
Classifier: Programming Language :: Python :: 3
Classifier: Programming Language :: Python :: 3.10
Classifier: Programming Language :: Python :: 3.8
Classifier: Programming Language :: Python :: 3.9
Requires-Dist: requests (>=2.27.1,<3.0.0)
Project-URL: Repository, https://github.com/tZ3ma/fogdb
